ase/__init__.py
ase/__main__.py
ase/atom.py
ase/atoms.py
ase/autoneb.py
ase/cell.py
ase/codes.py
ase/config.py
ase/constraints.py
ase/dependencies.py
ase/dimer.py
ase/dyneb.py
ase/eos.py
ase/filters.py
ase/formula.py
ase/neb.py
ase/neighborlist.py
ase/nomad.py
ase/outputs.py
ase/parallel.py
ase/phasediagram.py
ase/phonons.py
ase/pourbaix.py
ase/py.typed
ase/quaternions.py
ase/stress.py
ase/symbols.py
ase/thermochemistry.py
ase/units.py
ase/build/__init__.py
ase/build/attach.py
ase/build/bulk.py
ase/build/connected.py
ase/build/general_surface.py
ase/build/molecule.py
ase/build/niggli.py
ase/build/ribbon.py
ase/build/root.py
ase/build/rotate.py
ase/build/supercells.py
ase/build/surface.py
ase/build/surfaces_with_termination.py
ase/build/tools.py
ase/build/tube.py
ase/calculators/__init__.py
ase/calculators/abc.py
ase/calculators/abinit.py
ase/calculators/acemolecule.py
ase/calculators/acn.py
ase/calculators/aims.py
ase/calculators/amber.py
ase/calculators/bond_polarizability.py
ase/calculators/calculator.py
ase/calculators/castep.py
ase/calculators/checkpoint.py
ase/calculators/combine_mm.py
ase/calculators/counterions.py
ase/calculators/cp2k.py
ase/calculators/crystal.py
ase/calculators/demonnano.py
ase/calculators/dftb.py
ase/calculators/dftd3.py
ase/calculators/dmol.py
ase/calculators/eam.py
ase/calculators/elk.py
ase/calculators/emt.py
ase/calculators/espresso.py
ase/calculators/excitation_list.py
ase/calculators/fd.py
ase/calculators/ff.py
ase/calculators/fleur.py
ase/calculators/gamess_us.py
ase/calculators/gaussian.py
ase/calculators/genericfileio.py
ase/calculators/gromacs.py
ase/calculators/gulp.py
ase/calculators/h2morse.py
ase/calculators/harmonic.py
ase/calculators/idealgas.py
ase/calculators/lammpslib.py
ase/calculators/lammpsrun.py
ase/calculators/lj.py
ase/calculators/loggingcalc.py
ase/calculators/mixing.py
ase/calculators/mopac.py
ase/calculators/morse.py
ase/calculators/names.py
ase/calculators/nwchem.py
ase/calculators/octopus.py
ase-3.24.0.dist-info/COPYING
ase-3.24.0.dist-info/COPYING.LESSER
ase-3.24.0.dist-info/LICENSE
ase-3.24.0.dist-info/METADATA
ase-3.24.0.dist-info/WHEEL
ase-3.24.0.dist-info/entry_points.txt
ase-3.24.0.dist-info/top_level.txt
ase-3.24.0.dist-info/RECORD
