Metadata-Version: 2.1
Name: ase
Version: 3.24.0
Summary: Atomic Simulation Environment
Maintainer-email: ASE Community <ase-users@listserv.fysik.dtu.dk>
License: LGPLv2.1+
Project-URL: Homepage, https://wiki.fysik.dtu.dk/ase/
Project-URL: Repository, https://gitlab.com/ase/ase.git
Project-URL: Issues, https://gitlab.com/ase/ase/issues/
Classifier: Development Status :: 6 - Mature
Classifier: License :: OSI Approved :: GNU Lesser General Public License v2 or later (LGPLv2+)
Classifier: Intended Audience :: Science/Research
Classifier: Operating System :: OS Independent
Classifier: Programming Language :: Python :: 3
Classifier: Programming Language :: Python :: 3.9
Classifier: Programming Language :: Python :: 3.10
Classifier: Programming Language :: Python :: 3.11
Classifier: Programming Language :: Python :: 3.12
Classifier: Intended Audience :: Science/Research
Classifier: Topic :: Scientific/Engineering :: Physics
Requires-Python: >=3.9
License-File: LICENSE
License-File: COPYING
License-File: COPYING.LESSER
Requires-Dist: numpy>=1.19.5
Requires-Dist: scipy>=1.6.0
Requires-Dist: matplotlib>=3.3.4
Provides-Extra: docs
Requires-Dist: sphinx; extra == "docs"
Requires-Dist: sphinx_rtd_theme; extra == "docs"
Requires-Dist: pillow; extra == "docs"
Provides-Extra: test
Requires-Dist: pytest>=7.0.0; extra == "test"
Requires-Dist: pytest-xdist>=2.1.0; extra == "test"
Provides-Extra: spglib
Requires-Dist: spglib>=1.9; extra == "spglib"
